Workbook

Sheet IC 2024
K4: 0.05
K6: Meetings
B7: Nome | C7: Inicio | D7: Data | E7: Saída | F7: Manager | G7: Monthly Fee | H7: Success Fee | I7: Project Month | J7: Status | K7: Comments | L7: jan/24 | M7: fev/24 | N7: mar/24 | O7: abr/24 | P7: mai/24 | Q7: jun/24 | R7: jul/24 | S7: ago/24 | T7: set/24 | U7: out/24 | V7: nov/24 | W7: dez/24 | X7: Total
B8: Jossois | C8: 45597 | D8: 21 de novembro | F8: Isabela | G8: 1200 | H8: - | I8: 1 | J8: Active
B9: Grow Out | C9: 45627 | D9: 1 de dezembro | F9: Allen | G9: 1400 | H9: - | I9: 1 | J9: active | K9: começa em dezembro
B10: Tecnho store | C10: 45444 | D10: 20 de junho | F10: Allen | G10: 1500 | H10: 0.05 | I10: 1 | J10: Active
B11: Irmãos Rodrigues | C11: 45536 | D11: 23 de setembro | F11: Sérgio | G11: 1200 | H11: - | I11: 1 | J11: active
B12: Fapil | C12: 45536 | D12: 13 de set | F12: Sérgio | G12: 1500 | H12: - | I12: 2 | J12: Active
B13: Infinite Foundry | C13: 45536 | D13: 8 de setembro | F13: Marco | G13: 1900 | H13: - | I13: 0 | J13: Active | S13: 0 | X13: =Tabela1[[#This Row],[jan/24]]+Tabela1[[#This Row],[fev/24]]+Tabela1[[#This Row],[mar/24]]+Tabela1[[#This Row],[abr/24]]+Tabela1[[#This Row],[mai/24]]+Tabela1[[#This Row],[jun/24]]+Tabela1[[#This Row],[jul/24]]+Tabela1[[#This Row],[ago/24]]+Tabela1[[#This Row],[set/24]]+Tabela1[[#This Row],[out/24]]+Tabela1[[#This Row],[nov/24]]+Tabela1[[#This Row],[dez/24]] -> 0
B14: Delta | C14: 45444 | D14: 1 de junho | F14: Marco | G14: 1100 | H14: - | I14: 1 | J14: Active | K14: acaba dia 31 de Janiero | Q14: 0 | R14: 2 | S14: 1 | X14: =Tabela1[[#This Row],[jan/24]]+Tabela1[[#This Row],[fev/24]]+Tabela1[[#This Row],[mar/24]]+Tabela1[[#This Row],[abr/24]]+Tabela1[[#This Row],[mai/24]]+Tabela1[[#This Row],[jun/24]]+Tabela1[[#This Row],[jul/24]]+Tabela1[[#This Row],[ago/24]]+Tabela1[[#This Row],[set/24]]+Tabela1[[#This Row],[out/24]]+Tabela1[[#This Row],[nov/24]]+Tabela1[[#This Row],[dez/24]] -> 3
B15: Givachoice | C15: 45444 | D15: 27 de junho | F15: Isabela | G15: 1300 | H15: - | I15: 2 | J15: Active | Q15: 1 | R15: 2 | S15: 0 | T15: 2 | X15: =Tabela1[[#This Row],[jan/24]]+Tabela1[[#This Row],[fev/24]]+Tabela1[[#This Row],[mar/24]]+Tabela1[[#This Row],[abr/24]]+Tabela1[[#This Row],[mai/24]]+Tabela1[[#This Row],[jun/24]]+Tabela1[[#This Row],[jul/24]]+Tabela1[[#This Row],[ago/24]]+Tabela1[[#This Row],[set/24]]+Tabela1[[#This Row],[out/24]]+Tabela1[[#This Row],[nov/24]]+Tabela1[[#This Row],[dez/24]] -> 5
B16: Vittawood | C16: 45292 | D16: 8 de janeiro | F16: Marco | G16: 1100 | H16: - | I16: 7 | J16: Active | L16: 1 | M16: 3 | N16: 3 | O16: 2 | P16: 4 | Q16: 4 | R16: 3 | S16: 1 | X16: =Tabela1[[#This Row],[jan/24]]+Tabela1[[#This Row],[fev/24]]+Tabela1[[#This Row],[mar/24]]+Tabela1[[#This Row],[abr/24]]+Tabela1[[#This Row],[mai/24]]+Tabela1[[#This Row],[jun/24]]+Tabela1[[#This Row],[jul/24]]+Tabela1[[#This Row],[ago/24]]+Tabela1[[#This Row],[set/24]]+Tabela1[[#This Row],[out/24]]+Tabela1[[#This Row],[nov/24]]+Tabela1[[#This Row],[dez/24]] -> 21
B17: FJMPC | C17: 45323 | D17: 28 de fev | F17: Marco | G17: 1500 | H17: - | I17: 6 | J17: Active | M17: 2 | N17: 2 | O17: 3 | P17: 4 | Q17: 2 | R17: 1 | S17: 0 | X17: =Tabela1[[#This Row],[jan/24]]+Tabela1[[#This Row],[fev/24]]+Tabela1[[#This Row],[mar/24]]+Tabela1[[#This Row],[abr/24]]+Tabela1[[#This Row],[mai/24]]+Tabela1[[#This Row],[jun/24]]+Tabela1[[#This Row],[jul/24]]+Tabela1[[#This Row],[ago/24]]+Tabela1[[#This Row],[set/24]]+Tabela1[[#This Row],[out/24]]+Tabela1[[#This Row],[nov/24]]+Tabela1[[#This Row],[dez/24]] -> 14
B18: Ramagplast | C18: 45658 | D18: 8 de janeiro | F18: Sérgio | G18: 1000 | I18: 1 | J18: active | K18: começa em janeiro
B19: Alpine Seafood | C19: 45559 | D19: - | F19: Allen | G19: 1200 | H19: - | I19: 1 | J19: Active | S19: 0
B20: Artnovion | C20: 45559 | D20: - | F20: Marco | G20: 1200 | H20: - | I20: 1 | J20: Active | S20: 0
B21: Cyberx | C21: 45627 | D21: 45627 | F21: Marco | G21: 1900 | H21: - | I21: 1 | J21: Active
B22: SF Globallaser | C22: 45627 | D22: 16 de Dezembro | F22: Sérgio | G22: 1900 | H22: 0.03
B23: Exposerve | C23: 45658 | D23: 2 de janeiro | F23: Sérgio | G23: 1500 | I23: 3 | J23: active | K23: reunião de alinhamento em dez mas começa em janeiro
B24: Plasvip | C24: 45658 | D24: 7 de Janeiro | F24: Sergio | G24: 1900 | H24: 0.05 | I24: 1 | J24: active
B25: Recheio | C25: 45292 | D25: 1 de janeiro | F25: Marco | G25: 1100 | H25: - | I25: 3 | J25: active | L25: 4 | M25: 3 | N25: 2 | O25: 1 | P25: 2 | Q25: 3 | R25: 2 | S25: 0 | X25: =Tabela1[[#This Row],[jan/24]]+Tabela1[[#This Row],[fev/24]]+Tabela1[[#This Row],[mar/24]]+Tabela1[[#This Row],[abr/24]]+Tabela1[[#This Row],[mai/24]]+Tabela1[[#This Row],[jun/24]]+Tabela1[[#This Row],[jul/24]]+Tabela1[[#This Row],[ago/24]]+Tabela1[[#This Row],[set/24]]+Tabela1[[#This Row],[out/24]]+Tabela1[[#This Row],[nov/24]]+Tabela1[[#This Row],[dez/24]] -> 17
B26: Caixa Mágica | C26: 45658 | D26: 20 de janeiro | F26: Marco | G26: 1900 | H26: 0.05 | I26: 12 | J26: active
B27: José Luis Madeiras | C27: 45597 | D27: 20 de novembro | F27: Sérgio | G27: 1500 | H27: - | I27: 1 | J27: hold
B29: Farvoli | C29: 45444 | D29: 45454 | E29: 45962 | F29: Marco | G29: 1500 | H29: - | I29: 2 | J29: hold | Q29: 0 | R29: 4 | S29: 0 | X29: =Tabela1[[#This Row],[jan/24]]+Tabela1[[#This Row],[fev/24]]+Tabela1[[#This Row],[mar/24]]+Tabela1[[#This Row],[abr/24]]+Tabela1[[#This Row],[mai/24]]+Tabela1[[#This Row],[jun/24]]+Tabela1[[#This Row],[jul/24]]+Tabela1[[#This Row],[ago/24]]+Tabela1[[#This Row],[set/24]]+Tabela1[[#This Row],[out/24]]+Tabela1[[#This Row],[nov/24]]+Tabela1[[#This Row],[dez/24]] -> 4
B30: Arxi | C30: 45559 | D30: 45537 | E30: 45567 | F30: Marco | G30: 1500 | H30: - | I30: 1 | J30: hold | S30: 0
B31: Atelier Sabiina Design | C31: dec/2024 | D31: 45627 | E31: 45627 | F31: Sérgio | G31: 1500 | I31: 1 | J31: hold | K31: começa em dezembro
B32: GinT | C32: 45474 | D32: 45482 | E32: 45544 | F32: Allen | G32: 1500 | H32: - | I32: 3 | J32: hold | K32: estamos à espera do pagamento para continuar | R32: 2 | S32: 1 | T32: 3 | U32: 1 | X32: =Tabela1[[#This Row],[jan/24]]+Tabela1[[#This Row],[fev/24]]+Tabela1[[#This Row],[mar/24]]+Tabela1[[#This Row],[abr/24]]+Tabela1[[#This Row],[mai/24]]+Tabela1[[#This Row],[jun/24]]+Tabela1[[#This Row],[jul/24]]+Tabela1[[#This Row],[ago/24]]+Tabela1[[#This Row],[set/24]]+Tabela1[[#This Row],[out/24]]+Tabela1[[#This Row],[nov/24]]+Tabela1[[#This Row],[dez/24]] -> 7
B33: Mariano | C33: 45505 | D33: 45505 | E33: 45413 | F33: Isabela | G33: 800 | I33: 0 | J33: hold | K33: quer renovar, ainda n deu data | L33: 2 | M33: 1 | N33: 0 | O33: 0 | P33: 0 | Q33: 0 | R33: 0 | S33: 0 | X33: =Tabela1[[#This Row],[jan/24]]+Tabela1[[#This Row],[fev/24]]+Tabela1[[#This Row],[mar/24]]+Tabela1[[#This Row],[abr/24]]+Tabela1[[#This Row],[mai/24]]+Tabela1[[#This Row],[jun/24]]+Tabela1[[#This Row],[jul/24]]+Tabela1[[#This Row],[ago/24]]+Tabela1[[#This Row],[set/24]]+Tabela1[[#This Row],[out/24]]+Tabela1[[#This Row],[nov/24]]+Tabela1[[#This Row],[dez/24]] -> 3
B34: Artemola | C34: 45078 | D34: 45544 | E34: 45544 | F34: Allen | G34: 1100 | I34: 15 | J34: hold | K34: volta em fevereiro | L34: 3 | M34: 2 | N34: 1 | O34: 2 | P34: 0 | Q34: 0 | R34: 2 | S34: 0 | T34: 1 | U34: 1 | X34: =Tabela1[[#This Row],[jan/24]]+Tabela1[[#This Row],[fev/24]]+Tabela1[[#This Row],[mar/24]]+Tabela1[[#This Row],[abr/24]]+Tabela1[[#This Row],[mai/24]]+Tabela1[[#This Row],[jun/24]]+Tabela1[[#This Row],[jul/24]]+Tabela1[[#This Row],[ago/24]]+Tabela1[[#This Row],[set/24]]+Tabela1[[#This Row],[out/24]]+Tabela1[[#This Row],[nov/24]]+Tabela1[[#This Row],[dez/24]] -> 12
B36: Crafil | C36: 45444 | D36: 45450 | E36: 45598 | F36: Isabela | G36: 1500 | H36: - | I36: 1 | J36: Finished | Q36: 0 | R36: 5 | S36: 1 | X36: =Tabela1[[#This Row],[jan/24]]+Tabela1[[#This Row],[fev/24]]+Tabela1[[#This Row],[mar/24]]+Tabela1[[#This Row],[abr/24]]+Tabela1[[#This Row],[mai/24]]+Tabela1[[#This Row],[jun/24]]+Tabela1[[#This Row],[jul/24]]+Tabela1[[#This Row],[ago/24]]+Tabela1[[#This Row],[set/24]]+Tabela1[[#This Row],[out/24]]+Tabela1[[#This Row],[nov/24]]+Tabela1[[#This Row],[dez/24]] -> 6
B37: Creative Textile | C37: 45566 | D37: 45581 | E37: 45629 | F37: Isabela | G37: 1500 | H37: - | I37: 1 | J37: Finished
B38: Socutel | C38: 45566 | D38: 45587 | E38: 45656 | F38: Sérgio | G38: 1500 | H38: - | I38: 1 | J38: Finished
B39: Cubo Hotel | C39: 45597 | D39: 45623 | E39: 45656 | F39: Allen | G39: 1500 | H39: - | I39: 1 | J39: Finished | K39: começa dia 27 de dezembro
B40: Granidense | C40: 45444 | D40: 45445 | E40: 45623 | F40: Marco | G40: 1900 | H40: - | I40: 1 | J40: Finished | Q40: 0 | R40: 1 | S40: 2 | X40: =Tabela1[[#This Row],[jan/24]]+Tabela1[[#This Row],[fev/24]]+Tabela1[[#This Row],[mar/24]]+Tabela1[[#This Row],[abr/24]]+Tabela1[[#This Row],[mai/24]]+Tabela1[[#This Row],[jun/24]]+Tabela1[[#This Row],[jul/24]]+Tabela1[[#This Row],[ago/24]]+Tabela1[[#This Row],[set/24]]+Tabela1[[#This Row],[out/24]]+Tabela1[[#This Row],[nov/24]]+Tabela1[[#This Row],[dez/24]] -> 3
B41: Cubu Fitness | C41: 45536 | D41: 45539 | E41: 45625 | F41: Isabela | G41: 1200 | H41: - | I41: 0 | J41: Finished | T41: 1
B42: ANC Brands | C42: 45474 | D42: 45492 | E42: 45624 | F42: Sérgio | G42: 1500 | H42: - | I42: 1 | J42: Finished | R42: 2 | S42: 0 | X42: =Tabela1[[#This Row],[jan/24]]+Tabela1[[#This Row],[fev/24]]+Tabela1[[#This Row],[mar/24]]+Tabela1[[#This Row],[abr/24]]+Tabela1[[#This Row],[mai/24]]+Tabela1[[#This Row],[jun/24]]+Tabela1[[#This Row],[jul/24]]+Tabela1[[#This Row],[ago/24]]+Tabela1[[#This Row],[set/24]]+Tabela1[[#This Row],[out/24]]+Tabela1[[#This Row],[nov/24]]+Tabela1[[#This Row],[dez/24]] -> 2
B43: Freire Lobo | C43: 45566 | D43: 45581 | E43: 45612 | F43: Allen | G43: 1500 | H43: - | I43: 2 | J43: Finished
B44: Lambda Golf | C44: 45231 | F44: Bruno | G44: 1100 | I44: 3 | J44: Finished | L44: 2 | M44: 1 | N44: 0 | O44: 0 | P44: 0 | Q44: 0 | R44: 0 | S44: 0 | X44: 2
B45: VOLT | C45: 45200 | F45: Andres | G45: 600 | I45: 2 | J45: Finished | L45: 0 | M45: 0 | N45: 0 | O45: 0 | P45: 0 | Q45: 0 | R45: 0 | S45: 0 | X45: 2
B46: VECO | C46: 45078 | F46: Bruno | G46: 1100 | I46: 6 | J46: Finished | L46: 0 | M46: 0 | N46: 0 | O46: 0 | P46: 0 | Q46: 0 | R46: 0 | S46: 0 | X46: 3
B47: Salma Furniture | C47: 45017 | F47: Bruno | G47: 600 | I47: 6 | J47: Finished | L47: 0 | M47: 0 | N47: 0 | O47: 0 | P47: 0 | Q47: 0 | R47: 0 | S47: 0 | X47: 0
B48: Inventis | C48: 45170 | F48: Bruno | G48: 1100 | I48: 2 | J48: Finished | L48: 0 | M48: 0 | N48: 0 | O48: 0 | P48: 0 | Q48: 0 | R48: 0 | S48: 0 | X48: 0
B49: Celar | C49: 44805 | F49: Isabela | G49: 500 | I49: 18 | J49: Finished | L49: 2 | M49: 3 | N49: 2 | O49: 1 | P49: 1 | Q49: 0 | R49: 0 | S49: 0 | X49: =Tabela1[[#This Row],[jan/24]]+Tabela1[[#This Row],[fev/24]]+Tabela1[[#This Row],[mar/24]]+Tabela1[[#This Row],[abr/24]]+Tabela1[[#This Row],[mai/24]]+Tabela1[[#This Row],[jun/24]]+Tabela1[[#This Row],[jul/24]]+Tabela1[[#This Row],[ago/24]]+Tabela1[[#This Row],[set/24]]+Tabela1[[#This Row],[out/24]]+Tabela1[[#This Row],[nov/24]]+Tabela1[[#This Row],[dez/24]] -> 9
B50: Defontes | C50: 45108 | F50: Felipe | G50: 800 | I50: 8 | J50: Finished | L50: 0 | M50: 0 | N50: 0 | O50: 0 | P50: 0 | Q50: 0 | R50: 0 | S50: 0 | X50: =Tabela1[[#This Row],[jan/24]]+Tabela1[[#This Row],[fev/24]]+Tabela1[[#This Row],[mar/24]]+Tabela1[[#This Row],[abr/24]]+Tabela1[[#This Row],[mai/24]]+Tabela1[[#This Row],[jun/24]]+Tabela1[[#This Row],[jul/24]]+Tabela1[[#This Row],[ago/24]]+Tabela1[[#This Row],[set/24]]+Tabela1[[#This Row],[out/24]]+Tabela1[[#This Row],[nov/24]]+Tabela1[[#This Row],[dez/24]] -> 0
B51: Micromil | C51: 45231 | F51: Bruno | G51: 1100 | I51: 3 | J51: Finished | L51: 3 | M51: 3 | N51: 0 | O51: 0 | P51: 0 | Q51: 0 | R51: 0 | S51: 0 | X51: =Tabela1[[#This Row],[jan/24]]+Tabela1[[#This Row],[fev/24]]+Tabela1[[#This Row],[mar/24]]+Tabela1[[#This Row],[abr/24]]+Tabela1[[#This Row],[mai/24]]+Tabela1[[#This Row],[jun/24]]+Tabela1[[#This Row],[jul/24]]+Tabela1[[#This Row],[ago/24]]+Tabela1[[#This Row],[set/24]]+Tabela1[[#This Row],[out/24]]+Tabela1[[#This Row],[nov/24]]+Tabela1[[#This Row],[dez/24]] -> 6
B52: RJB Home | C52: 45292 | F52: Marco | G52: 800 | I52: 5 | J52: Finished | L52: 2 | M52: 3 | N52: 4 | O52: 1 | P52: 2 | Q52: 1 | R52: 0 | S52: 0 | X52: 1
B53: Freak Chic | C53: 45323 | F53: Isabela | G53: 1100 | I53: 2 | J53: Finished | L53: 2 | M53: 1 | N53: 0 | O53: 0 | P53: 0 | Q53: 0 | R53: 0 | S53: 0 | X53: 2
B54: Foco Criativo | C54: 45108 | F54: Isabela | G54: 1100 | I54: 4 | J54: Finished | L54: 0 | M54: 0 | N54: 0 | O54: 0 | P54: 0 | Q54: 0 | R54: 0 | S54: 0 | X54: 0
B55: Timbera | C55: 45170 | F55: Andres | G55: 0 | I55: 0 | J55: Finished | L55: 0 | M55: 0 | N55: 0 | O55: 0 | P55: 0 | Q55: 0 | R55: 0 | S55: 0 | X55: 0
B56: Mirapack | C56: 45200 | F56: Isabela | G56: 1000 | I56: 2 | J56: Finished | L56: 0 | M56: 0 | N56: 0 | O56: 0 | P56: 0 | Q56: 0 | R56: 0 | S56: 0 | X56: 0
B57: Já te disse | C57: 44986 | F57: Isabela | G57: 400 | I57: 6 | J57: Finished | L57: 0 | M57: 0 | N57: 0 | O57: 0 | P57: 0 | Q57: 0 | R57: 0 | S57: 0 | X57: 0
B58: Gracia Sofia | C58: 45170 | F58: Isabela | G58: 700 | I58: 1 | J58: Finished | L58: 0 | M58: 0 | N58: 0 | O58: 0 | P58: 0 | Q58: 0 | R58: 0 | S58: 0 | X58: 0
B59: Gold Nutrition | C59: 44896 | F59: Andres | G59: 400 | I59: 10 | J59: Finished | L59: 0 | M59: 0 | N59: 0 | O59: 0 | P59: 0 | Q59: 0 | R59: 0 | S59: 0 | X59: 0
B60: Metallik | C60: 45474 | F60: Bruno | G60: 400 | I60: 5 | J60: Finished | L60: 0 | M60: 0 | N60: 0 | O60: 0 | P60: 0 | Q60: 0 | R60: 0 | S60: 0 | X60: 0
B61: Kiba Candles | C61: 45231 | F61: Isabela | G61: 1100 | I61: 2 | J61: Finished | L61: 2 | M61: 0 | N61: 0 | O61: 0 | P61: 0 | Q61: 0 | R61: 0 | S61: 0 | X61: 0
B62: Camellia | C62: 45323 | F62: Isabela | G62: 1100 | I62: 6 | J62: Finished | M62: 0 | N62: 1 | O62: 1 | P62: 0 | Q62: 0 | R62: 0
B63: JF Almeida | C63: 45536 | D63: 45553 | F63: Sérgio | G63: 1500 | I63: 2 | J63: Finished
B64: FM Texteis | C64: 45323 | F64: Isabela | G64: 900 | J64: Finished | M64: 0 | N64: 0 | O64: 1 | P64: 1 | R64: 0 | S64: 2 | X64: =Tabela1[[#This Row],[jan/24]]+Tabela1[[#This Row],[fev/24]]+Tabela1[[#This Row],[mar/24]]+Tabela1[[#This Row],[abr/24]]+Tabela1[[#This Row],[mai/24]]+Tabela1[[#This Row],[jun/24]]+Tabela1[[#This Row],[jul/24]]+Tabela1[[#This Row],[ago/24]]+Tabela1[[#This Row],[set/24]]+Tabela1[[#This Row],[out/24]]+Tabela1[[#This Row],[nov/24]]+Tabela1[[#This Row],[dez/24]] -> 4
B65: Gema | C65: 45413 | F65: Isabela | G65: 1900 | I65: 2 | J65: Finished | M65: 1* | R65: 3 | S65: 1
B66: Farimovel | C66: 45474 | F66: Vânia | G66: 1500 | I66: 1 | J66: Finished | R66: 3 | S66: 2 | T66: 3
B67: New Mattress | C67: 45383 | F67: Vânia | G67: 1500 | I67: 3 | J67: Finished | O67: 0 | P67: 1 | Q67: 3 | R67: 2 | S67: 2 | T67: 1 | X67: =Tabela1[[#This Row],[jan/24]]+Tabela1[[#This Row],[fev/24]]+Tabela1[[#This Row],[mar/24]]+Tabela1[[#This Row],[abr/24]]+Tabela1[[#This Row],[mai/24]]+Tabela1[[#This Row],[jun/24]]+Tabela1[[#This Row],[jul/24]]+Tabela1[[#This Row],[ago/24]]+Tabela1[[#This Row],[set/24]]+Tabela1[[#This Row],[out/24]]+Tabela1[[#This Row],[nov/24]]+Tabela1[[#This Row],[dez/24]] -> 9
B68: Cácio | C68: 45444 | F68: Vânia | G68: 1500 | I68: 1 | J68: Finished | Q68: 0 | R68: 6 | S68: 0 | X68: =Tabela1[[#This Row],[jan/24]]+Tabela1[[#This Row],[fev/24]]+Tabela1[[#This Row],[mar/24]]+Tabela1[[#This Row],[abr/24]]+Tabela1[[#This Row],[mai/24]]+Tabela1[[#This Row],[jun/24]]+Tabela1[[#This Row],[jul/24]]+Tabela1[[#This Row],[ago/24]]+Tabela1[[#This Row],[set/24]]+Tabela1[[#This Row],[out/24]]+Tabela1[[#This Row],[nov/24]]+Tabela1[[#This Row],[dez/24]] -> 6
B69: Focor | C69: 45383 | F69: Vânia | G69: 500 | I69: 3 | J69: Finished | O69: 0 | P69: 2 | Q69: 3 | R69: 4 | S69: 0 | X69: =Tabela1[[#This Row],[jan/24]]+Tabela1[[#This Row],[fev/24]]+Tabela1[[#This Row],[mar/24]]+Tabela1[[#This Row],[abr/24]]+Tabela1[[#This Row],[mai/24]]+Tabela1[[#This Row],[jun/24]]+Tabela1[[#This Row],[jul/24]]+Tabela1[[#This Row],[ago/24]]+Tabela1[[#This Row],[set/24]]+Tabela1[[#This Row],[out/24]]+Tabela1[[#This Row],[nov/24]]+Tabela1[[#This Row],[dez/24]] -> 9
B70: Indinor | C70: 45383 | F70: Vânia | G70: 500 | I70: 3 | J70: Finished | O70: 0 | P70: 2 | Q70: 1 | R70: 1 | S70: 0 | X70: =Tabela1[[#This Row],[jan/24]]+Tabela1[[#This Row],[fev/24]]+Tabela1[[#This Row],[mar/24]]+Tabela1[[#This Row],[abr/24]]+Tabela1[[#This Row],[mai/24]]+Tabela1[[#This Row],[jun/24]]+Tabela1[[#This Row],[jul/24]]+Tabela1[[#This Row],[ago/24]]+Tabela1[[#This Row],[set/24]]+Tabela1[[#This Row],[out/24]]+Tabela1[[#This Row],[nov/24]]+Tabela1[[#This Row],[dez/24]] -> 4
B71: Vale de Barqueiros | C71: 45383 | F71: Vânia | G71: 500 | I71: 3 | J71: Finished | O71: 0 | P71: 1 | Q71: 1 | R71: 0 | S71: 0 | X71: =Tabela1[[#This Row],[jan/24]]+Tabela1[[#This Row],[fev/24]]+Tabela1[[#This Row],[mar/24]]+Tabela1[[#This Row],[abr/24]]+Tabela1[[#This Row],[mai/24]]+Tabela1[[#This Row],[jun/24]]+Tabela1[[#This Row],[jul/24]]+Tabela1[[#This Row],[ago/24]]+Tabela1[[#This Row],[set/24]]+Tabela1[[#This Row],[out/24]]+Tabela1[[#This Row],[nov/24]]+Tabela1[[#This Row],[dez/24]] -> 2
B72: Fravizel | C72: 44896 | F72: Allen | G72: 650 | I72: 20 | J72: Finished | Q72: 1 | R72: 1 | S72: 0 | X72: =Tabela1[[#This Row],[jan/24]]+Tabela1[[#This Row],[fev/24]]+Tabela1[[#This Row],[mar/24]]+Tabela1[[#This Row],[abr/24]]+Tabela1[[#This Row],[mai/24]]+Tabela1[[#This Row],[jun/24]]+Tabela1[[#This Row],[jul/24]]+Tabela1[[#This Row],[ago/24]]+Tabela1[[#This Row],[set/24]]+Tabela1[[#This Row],[out/24]]+Tabela1[[#This Row],[nov/24]]+Tabela1[[#This Row],[dez/24]] -> 2
B73: Katoa Lighting | C73: 45170 | F73: Vânia | G73: 1000 | I73: 10 | J73: Finished | L73: 2 | M73: 3 | N73: 2 | O73: 1 | P73: 1 | Q73: 2 | R73: 4 | S73: 0 | X73: =Tabela1[[#This Row],[jan/24]]+Tabela1[[#This Row],[fev/24]]+Tabela1[[#This Row],[mar/24]]+Tabela1[[#This Row],[abr/24]]+Tabela1[[#This Row],[mai/24]]+Tabela1[[#This Row],[jun/24]]+Tabela1[[#This Row],[jul/24]]+Tabela1[[#This Row],[ago/24]]+Tabela1[[#This Row],[set/24]]+Tabela1[[#This Row],[out/24]]+Tabela1[[#This Row],[nov/24]]+Tabela1[[#This Row],[dez/24]] -> 15
B74: 44 | G74: =G40+#REF!+G65+G66+G62+G13+G14+G36+G16+#REF!+#REF!+G73+G67+G68+G69+G70+G71+G33+G42+G72+#REF!+G34+G64+G15+G17+#REF!+G44+G49+G51+G52+G53 -> #REF! | I74: =(I40+#REF!+I65+I66+I62+I13+I14+I36+I16+#REF!+#REF!+I73+I67+I68+I69+I70+I71+I33+I42+I72+#REF!+I34+I64+I15+I17+#REF!)/26 -> #REF!
B75: 26 | G75: =G40+#REF!+G65+G66+G62+G13+G14+G36+G16+#REF!+#REF!+G73+G67+G68+G69+G70+G71+G33+G42+G72+#REF!+G34+G64+G15+G17+#REF! -> #REF! | L75: =L40+#REF!+L65+L66+L62+L13+L14+L36+L16+#REF!+#REF!+L73+L67+L68+L69+L70+L71+L33+L42+L72+#REF!+L34+L64+L15+L17+#REF!+L44+L49+L51+L52+L53 -> #REF! | M75: =M40+#REF!+M65+M66+M62+M13+M14+M36+M16+#REF!+#REF!+M73+M67+M68+M69+M70+M71+M33+M42+M72+#REF!+M34+M64+M15+M17+#REF!+M44+M49+M51+M52+M53 -> #REF! | N75: =N40+#REF!+N65+N66+N62+N13+N14+N36+N16+#REF!+#REF!+N73+N67+N68+N69+N70+N71+N33+N42+N72+#REF!+N34+N64+N15+N17+#REF!+N44+N49+N51+N52+N53 -> #REF! | O75: =O40+#REF!+O65+O66+O62+O13+O14+O36+O16+#REF!+#REF!+O73+O67+O68+O69+O70+O71+O33+O42+O72+#REF!+O34+O64+O15+O17+#REF!+O44+O49+O51+O52+O53 -> #REF! | P75: =P40+#REF!+P65+P66+P62+P13+P14+P36+P16+#REF!+#REF!+P73+P67+P68+P69+P70+P71+P33+P42+P72+#REF!+P34+P64+P15+P17+#REF!+P44+P49+P51+P52+P53 -> #REF! | Q75: =Q40+#REF!+Q65+Q66+Q62+Q13+Q14+Q36+Q16+#REF!+#REF!+Q73+Q67+Q68+Q69+Q70+Q71+Q33+Q42+Q72+#REF!+Q34+Q64+Q15+Q17+#REF!+Q44+Q49+Q51+Q52+Q53 -> #REF! | R75: =R40+#REF!+R65+R66+R62+R13+R14+R36+R16+#REF!+#REF!+R73+R67+R68+R69+R70+R71+R33+R42+R72+#REF!+R34+R64+R15+R17+#REF!+R44+R49+R51+R52+R53 -> #REF! | S75: =S40+#REF!+S65+S66+S62+S13+S14+S36+S16+#REF!+#REF!+S73+S67+S68+S69+S70+S71+S33+S42+S72+#REF!+S34+S64+S15+S17+#REF!+S44+S49+S51+S52+S53 -> #REF! | ... X75: =X40+#REF!+X65+X66+X62+X13+X14+X36+X16+#REF!+#REF!+X73+X67+X68+X69+X70+X71+X33+X42+X72+#REF!+X34+X64+X15+X17+#REF!+X44+X49+X51+X52+X53 -> #REF!
K76: =(L40+#REF!+L65+L66+L62+L13+L14+L36+L16+#REF!+#REF!+L73+L67+L68+L69+L70+L71+L33+L42+L72+#REF!+L34+L64+L15+L17+#REF!+L44+L49+L51+L52+L53)/12 -> #REF! | L76: =(M40+#REF!+M65+M66+M62+M13+M14+M36+M16+#REF!+#REF!+M73+M67+M68+M69+M70+M71+M33+M42+M72+#REF!+M34+M64+M15+M17+#REF!+M44+M49+M51+M52+M53)/14 -> #REF! | M76: =(N40+#REF!+N65+N66+N62+N13+N14+N36+N16+#REF!+#REF!+N73+N67+N68+N69+N70+N71+N33+N42+N72+#REF!+N34+N64+N15+N17+#REF!+N44+N49+N51+N52+N53)/11 -> #REF! | N76: =(O40+#REF!+O65+O66+O62+O13+O14+O36+O16+#REF!+#REF!+O73+O67+O68+O69+O70+O71+O33+O42+O72+#REF!+O34+O64+O15+O17+#REF!+O44+O49+O51+O52+O53)/15 -> #REF! | O76: =(P40+#REF!+P65+P66+P62+P13+P14+P36+P16+#REF!+#REF!+P73+P67+P68+P69+P70+P71+P33+P42+P72+#REF!+P34+P64+P15+P17+#REF!+P44+P49+P51+P52+P53)/16 -> #REF! | P76: =(Q40+#REF!+Q65+Q66+Q62+Q13+Q14+Q36+Q16+#REF!+#REF!+Q73+Q67+Q68+Q69+Q70+Q71+Q33+Q42+Q72+#REF!+Q34+Q64+Q15+Q17+#REF!+Q44+Q49+Q51+Q52+Q53)/22 -> #REF! | Q76: =(R40+#REF!+R65+R66+R62+R13+R14+R36+R16+#REF!+#REF!+R73+R67+R68+R69+R70+R71+R33+R42+R72+#REF!+R34+R64+R15+R17+#REF!+R44+R49+R51+R52+R53)/24 -> #REF! | R76: =(S40+#REF!+S65+S66+S62+S13+S14+S36+S16+#REF!+#REF!+S73+S67+S68+S69+S70+S71+S33+S42+S72+#REF!+S34+S64+S15+S17+#REF!+S44+S49+S51+S52+S53)/23 -> #REF! | S76: =(T40+#REF!+T65+T66+T62+T13+T14+T36+T16+#REF!+#REF!+T73+T67+T68+T69+T70+T71+T33+T42+T72+#REF!+T34+T64+T15+T17+#REF!+T44+T49+T51+T52+T53)/12 -> #REF! | T76: =(U40+#REF!+U65+U66+U62+U13+U14+U36+U16+#REF!+#REF!+U73+U67+U68+U69+U70+U71+U33+U42+U72+#REF!+U34+U64+U15+U17+#REF!+U44+U49+U51+U52+U53)/12 -> #REF! | U76: =(V40+#REF!+V65+V66+V62+V13+V14+V36+V16+#REF!+#REF!+V73+V67+V68+V69+V70+V71+V33+V42+V72+#REF!+V34+V64+V15+V17+#REF!+V44+V49+V51+V52+V53)/12 -> #REF! | V76: =(W40+#REF!+W65+W66+W62+W13+W14+W36+W16+#REF!+#REF!+W73+W67+W68+W69+W70+W71+W33+W42+W72+#REF!+W34+W64+W15+W17+#REF!+W44+W49+W51+W52+W53)/12 -> #REF! | W76: =(X40+#REF!+X65+X66+X62+X13+X14+X36+X16+#REF!+#REF!+X73+X67+X68+X69+X70+X71+X33+X42+X72+#REF!+X34+X64+X15+X17+#REF!+X44+X49+X51+X52+X53)/30 -> #REF!
W80: =X40+X13+X14+X16+#REF!+X17+#REF!+X52 -> #REF!
W81: =#REF!+X65+X62+X36+X33+X42+X15+X49+X53 -> #REF!
W82: =X36+X16+#REF!+#REF!+X64 -> #REF!
W83: =X40+X69+X15+#REF! -> #REF!
B84: 2024 | C84: Entradas projetos | W84: 0
B85: Janeiro | C85: =COUNT(C16,C52,C25) -> 3 | W85: 8
B86: Fevereiro | C86: =COUNT(C53,C62,C64) -> 3 | W86: 3
B87: Março | C87: 0
B88: Abril | C88: =COUNT(C69,C70,C71) -> 3
B89: Maio | C89: =COUNT(C65) -> 1
B90: Junho | C90: =COUNT(C10,C14,C15,C29,C36,C68) -> 6
B91: Julho | C91: =COUNT(C29,C32,C42,C50,C54,C60,C66) -> 7
B92: Agosto | C92: =COUNT(C33) -> 1
B93: Setembro | C93: =COUNT(C11,C12,C13,C19,C20,C30,C41,C63) -> 8
B94: Outubro | C94: =COUNT(C37,C38,C43) -> 3
B95: Novembro | C95: =COUNT(C8,C27,C39) -> 3
B96: Dezembro | C96: =COUNT(C9,C21,C22,C31) -> 3
B100: 2024 | C100: Saída projetos
B101: Janeiro | C101: 0
B102: Fevereiro | C102: 0
B103: Março | C103: 0
B104: Abril | C104: 0
B105: Maio | C105: 0
B106: Junho | C106: 0
B107: Julho | C107: 0
B108: Agosto | C108: 0
B109: Setembro | C109: =COUNT(E32,E34) -> 2
B110: Outubro | C110: =COUNT(E30) -> 1
B111: Novembro | C111: =COUNT(E29,E36,E40,E41,E42,E43) -> 6
B112: Dezembro | C112: =COUNT(E39,E38,E37,E31) -> 4

Sheet IC 2025
L4: 0.05
L6: Meetings
B7: Nome | C7: Inicio | D7: Data entrada | E7: Data 2 | F7: Meses | G7: Manager | H7: Monthly Fee | I7: Success Fee | J7: Project Month | K7: Status | L7: Comments | M7: jan/24 | N7: fev/24 | O7: mar/24 | P7: abr/24 | Q7: mai/24 | R7: jun/24 | S7: jul/24 | T7: ago/24 | U7: set/24 | V7: out/24 | W7: nov/24 | X7: dez/24 | Y7: Total
B8: Grow Out | C8: 2024 Dezembro | D8: 45627 | E8: =TODAY() -> 46171 | F8: =DATEDIF(Tabela153[[#This Row],[Data entrada]],Tabela153[[#This Row],[Data 2]], "M") -> 17 | G8: Allen | H8: 1400 | I8: - | J8: 1 | K8: Active
B9: Delta | C9: 2025 Junho | D9: 45444 | E9: =TODAY() -> 46171 | F9: =DATEDIF(Tabela153[[#This Row],[Data entrada]],Tabela153[[#This Row],[Data 2]], "M") -> 23 | G9: Marco | H9: 1100 | I9: - | J9: 1 | K9: Active
B10: FJMPC | C10: 2024 Fevereiro | D10: 45350 | E10: =TODAY() -> 46171 | F10: =DATEDIF(Tabela153[[#This Row],[Data entrada]],Tabela153[[#This Row],[Data 2]], "M") -> 27 | G10: Marco | H10: 1500 | I10: - | J10: 6 | K10: Active
B11: Alpine Seafood | C11: 2024 Setembro | D11: 45536 | E11: =TODAY() -> 46171 | G11: Allen | H11: 1200 | I11: - | J11: 1 | K11: Active
B12: Artnovion | C12: 2024 Setembro | D12: 45536 | E12: =TODAY() -> 46171 | G12: Manel | H12: 1200 | I12: - | J12: 1 | K12: Active
B13: Plasvip | C13: 2025 Janeiro | D13: 45664 | E13: =TODAY() -> 46171 | F13: =DATEDIF(Tabela153[[#This Row],[Data entrada]],Tabela153[[#This Row],[Data 2]], "M") -> 16 | G13: Sérgio | H13: 1900 | I13: 0.05 | J13: 1 | K13: Active
B14: Recheio | C14: 2024 Janeiro | D14: 45292 | E14: =TODAY() -> 46171 | F14: =DATEDIF(Tabela153[[#This Row],[Data entrada]],Tabela153[[#This Row],[Data 2]], "M") -> 28 | G14: Marco | H14: 1100 | I14: - | J14: 3 | K14: Active
B15: Caixa Mágica | C15: 2025 Janeiro | D15: 45677 | E15: =TODAY() -> 46171 | F15: =DATEDIF(Tabela153[[#This Row],[Data entrada]],Tabela153[[#This Row],[Data 2]], "M") -> 16 | G15: Marco | H15: 1900 | I15: 0.05 | J15: 12 | K15: Active
B16: Aquecinox | C16: 2025 Fevereiro | D16: 45694 | E16: =TODAY() -> 46171 | F16: =DATEDIF(Tabela153[[#This Row],[Data entrada]],Tabela153[[#This Row],[Data 2]], "M") -> 15 | G16: Manel | H16: 1500 | K16: Active
B17: Core Concept | C17: 2025 Março | D17: 45719 | E17: =TODAY() -> 46171 | F17: =DATEDIF(Tabela153[[#This Row],[Data entrada]],Tabela153[[#This Row],[Data 2]], "M") -> 14 | G17: Sérgio | H17: 1900 | I17: 0.05 | K17: Active | M17: =COUNTIFS('Reuniões 2025'!I:I, B17) -> 52 | Y17: =COUNTIFS('Reuniões 2025'!I:I, B17) -> 52
B18: Qucaan | C18: 2025 Março | D18: 45721 | E18: =TODAY() -> 46171 | F18: =DATEDIF(Tabela153[[#This Row],[Data entrada]],Tabela153[[#This Row],[Data 2]], "M") -> 14 | G18: Sérgio | H18: 1500 | K18: Active | M18: =COUNTIFS('Reuniões 2025'!I:I, B18) -> 18 | Y18: =COUNTIFS('Reuniões 2025'!I:I, B18) -> 18
B19: Texteis Penedo | C19: 2025 Março | D19: 45729 | E19: =TODAY() -> 46171 | F19: =DATEDIF(Tabela153[[#This Row],[Data entrada]],Tabela153[[#This Row],[Data 2]], "M") -> 14 | G19: Sofia | H19: 1900 | I19: 0.05 | K19: Active | M19: =COUNTIFS('Reuniões 2025'!I:I, B19) -> 0 | Y19: =COUNTIFS('Reuniões 2025'!I:I, B19) -> 0
B20: Aronlight | C20: 2025 Março | D20: 45720 | E20: =TODAY() -> 46171 | F20: =DATEDIF(Tabela153[[#This Row],[Data entrada]],Tabela153[[#This Row],[Data 2]], "M") -> 14 | G20: Allen | H20: 1300 | I20: 0.065 | K20: Active | M20: =COUNTIFS('Reuniões 2025'!I:I, B20) -> 18 | Y20: =COUNTIFS('Reuniões 2025'!I:I, B20) -> 18
B21: Acushla | C21: 2025 Abril | D21: 45754 | E21: =TODAY() -> 46171 | F21: =DATEDIF(Tabela153[[#This Row],[Data entrada]],Tabela153[[#This Row],[Data 2]], "M") -> 13 | G21: Allen | H21: 1250 | I21: 0.05 | K21: active | M21: =COUNTIFS('Reuniões 2025'!I:I, B21) -> 18 | Y21: =COUNTIFS('Reuniões 2025'!I:I, B21) -> 18
B22: Tetribérica | C22: 2025 Abril | D22: 45754 | E22: =TODAY() -> 46171 | F22: =DATEDIF(Tabela153[[#This Row],[Data entrada]],Tabela153[[#This Row],[Data 2]], "M") -> 13 | G22: Sofia | H22: 1250 | I22: 0.05 | K22: Active | M22: =COUNTIFS('Reuniões 2025'!I:I, B22) -> 17 | Y22: =COUNTIFS('Reuniões 2025'!I:I, B22) -> 17
B23: Genan, S.A. | C23: 2025 Abril | D23: 45751 | E23: =TODAY() -> 46171 | F23: =DATEDIF(Tabela153[[#This Row],[Data entrada]],Tabela153[[#This Row],[Data 2]], "M") -> 13 | G23: Sérgio | H23: 1900 | I23: 0.05 | K23: active | M23: =COUNTIFS('Reuniões 2025'!I:I, B23) -> 0 | Y23: =COUNTIFS('Reuniões 2025'!I:I, B23) -> 0
B24: Ricarle Stone | C24: 2025 Abril | D24: 45751 | E24: =TODAY() -> 46171 | F24: =DATEDIF(Tabela153[[#This Row],[Data entrada]],Tabela153[[#This Row],[Data 2]], "M") -> 13 | G24: Sérgio | H24: 1500 | I24: 0.05 | K24: Active | M24: =COUNTIFS('Reuniões 2025'!I:I, B24) -> 33 | Y24: =COUNTIFS('Reuniões 2025'!I:I, B24) -> 33
B25: OneOutfit | C25: 2025 Abril | D25: 45776 | E25: =TODAY() -> 46171 | G25: Sofia | H25: 1000 | I25: 0.03 | M25: =COUNTIFS('Reuniões 2025'!I:I, B25) -> 3 | Y25: =COUNTIFS('Reuniões 2025'!I:I, B25) -> 3
B26: Termopainel | C26: 2025 Abril | D26: 45763 | E26: =TODAY() -> 46171 | G26: Sofia | H26: 1600 | I26: 0.01 | M26: =COUNTIFS('Reuniões 2025'!I:I, B26) -> 36 | Y26: =COUNTIFS('Reuniões 2025'!I:I, B26) -> 36
B27: Têxtil Nortenha | C27: 2025 Abril | D27: 45763 | E27: =TODAY() -> 46171 | G27: Sofia | H27: 1500 | I27: 0.05 | M27: =COUNTIFS('Reuniões 2025'!I:I, B27) -> 7 | Y27: =COUNTIFS('Reuniões 2025'!I:I, B27) -> 7
B28: Biocheers | C28: 2025 Maio | D28: 45789 | E28: =TODAY() -> 46171 | F28: =DATEDIF(Tabela153[[#This Row],[Data entrada]],Tabela153[[#This Row],[Data 2]], "M") -> 12 | G28: Allen | H28: 1500 | I28: 0.05 | M28: =COUNTIFS('Reuniões 2025'!I:I, B28) -> 10 | Y28: =COUNTIFS('Reuniões 2025'!I:I, B28) -> 10
B29: Santa Marta | C29: 2025 Maio | D29: 45792 | E29: =TODAY() -> 46171 | F29: =DATEDIF(Tabela153[[#This Row],[Data entrada]],Tabela153[[#This Row],[Data 2]], "M") -> 12 | G29: Sofia | H29: 1500 | I29: 0.05 | M29: =COUNTIFS('Reuniões 2025'!I:I, B29) -> 1 | Y29: =COUNTIFS('Reuniões 2025'!I:I, B29) -> 1
B30: wTVision | C30: 2025 Junho | D30: 45811 | E30: =TODAY() -> 46171 | G30: Manuel | H30: 1900 | I30: 0.05 | M30: =COUNTIFS('Reuniões 2025'!I:I, B30) -> 9 | Y30: =COUNTIFS('Reuniões 2025'!I:I, B30) -> 9
B31: Drops Nazaré | C31: 2025 Junho | D31: 45825 | E31: =TODAY() -> 46171 | G31: Sofia | H31: 1500 | I31: 0.05 | M31: =COUNTIFS('Reuniões 2025'!I:I, B31) -> 14 | Y31: =COUNTIFS('Reuniões 2025'!I:I, B31) -> 14
B32: Residence | C32: 2025 Julho | D32: 45840 | E32: =TODAY() -> 46171 | G32: Allen | H32: 1500 | I32: 0.05 | M32: =COUNTIFS('Reuniões 2025'!I:I, B32) -> 9 | Y32: =COUNTIFS('Reuniões 2025'!I:I, B32) -> 9
B33: Happy Probability | C33: 2025 Julho | D33: 45841 | E33: =TODAY() -> 46171 | G33: Sofia | H33: 1500 | I33: 0.05 | M33: =COUNTIFS('Reuniões 2025'!I:I, B33) -> 9 | Y33: =COUNTIFS('Reuniões 2025'!I:I, B33) -> 9
E34: =TODAY() -> 46171 | F34: =DATEDIF(Tabela153[[#This Row],[Data entrada]],Tabela153[[#This Row],[Data 2]], "M") -> 1516
B35: Exposerve | C35: 2025 Janeiro | D35: 45659 | E35: 45754 | F35: =DATEDIF(Tabela153[[#This Row],[Data entrada]],Tabela153[[#This Row],[Data 2]], "M") -> 3 | G35: Sérgio | H35: 1500 | J35: 3 | K35: hold
B36: Ramagplast | C36: 45658 | D36: 45665 | E36: 45747 | F36: =DATEDIF(Tabela153[[#This Row],[Data entrada]],Tabela153[[#This Row],[Data 2]], "M") -> 2 | G36: Sérgio | H36: 1000 | J36: 1 | K36: hold
B37: José Luis Madeiras | C37: 45597 | D37: 45616 | E37: 45708 | F37: =DATEDIF(Tabela153[[#This Row],[Data entrada]],Tabela153[[#This Row],[Data 2]], "M") -> 3 | G37: Sérgio | H37: 1500 | I37: - | J37: 1 | K37: hold
B38: Farvoli | C38: 45444 | D38: 45454 | E38: 45576 | F38: =DATEDIF(Tabela153[[#This Row],[Data entrada]],Tabela153[[#This Row],[Data 2]], "M") -> 4 | G38: Marco | H38: 1500 | I38: - | J38: 2 | K38: hold
B39: Arxi | C39: 45559 | D39: 45537 | E39: 45567 | F39: =DATEDIF(Tabela153[[#This Row],[Data entrada]],Tabela153[[#This Row],[Data 2]], "M") -> 1 | G39: Marco | H39: 1500 | I39: - | J39: 1 | K39: hold
B40: Atelier Sabiina Design | C40: dec/2024 | D40: 45627 | E40: 45627 | F40: =DATEDIF(Tabela153[[#This Row],[Data entrada]],Tabela153[[#This Row],[Data 2]], "M") -> 0 | G40: Sérgio | H40: 1500 | J40: 1 | K40: hold
B41: GinT | C41: 45474 | D41: 45482 | E41: 45544 | F41: =DATEDIF(Tabela153[[#This Row],[Data entrada]],Tabela153[[#This Row],[Data 2]], "M") -> 2 | G41: Allen | H41: 1500 | I41: - | J41: 3 | K41: hold | L41: estamos à espera do pagamento para continuar
B42: Mariano | C42: 45505 | D42: 45505 | E42: 45413 | G42: Isabela | H42: 800 | J42: 0 | K42: hold | L42: quer renovar, ainda n deu data
B43: Artemola | C43: 45078 | D43: 45444 | E43: 45544 | G43: Allen | H43: 1100 | J43: 15 | K43: hold | L43: volta em fevereiro
B44: Jossois | C44: 45597 | D44: 45617 | E44: 45737 | F44: =DATEDIF(Tabela153[[#This Row],[Data entrada]],Tabela153[[#This Row],[Data 2]], "M") -> 4 | G44: Manel | H44: 1200 | I44: - | J44: 1 | K44: hold
B45: Tecnho store | C45: 45444 | D45: 45463 | E45: 45736 | F45: =DATEDIF(Tabela153[[#This Row],[Data entrada]],Tabela153[[#This Row],[Data 2]], "M") -> 9 | G45: Allen | H45: 1500 | I45: 0.05 | J45: 1 | K45: hold
B46: Cyberx | C46: 45627 | D46: 45627 | E46: 45744 | F46: =DATEDIF(Tabela153[[#This Row],[Data entrada]],Tabela153[[#This Row],[Data 2]], "M") -> 3 | G46: Marco | H46: 1900 | I46: - | J46: 1 | K46: hold
E47: =TODAY() -> 46171 | F47: =DATEDIF(Tabela153[[#This Row],[Data entrada]],Tabela153[[#This Row],[Data 2]], "M") -> 1516
B48: Vittawood | C48: 2024 Janeiro | D48: 45299 | E48: 45747 | F48: =DATEDIF(Tabela153[[#This Row],[Data entrada]],Tabela153[[#This Row],[Data 2]], "M") -> 14 | G48: Marco | H48: 1100 | I48: - | J48: 7 | K48: concluded
B49: Givachoice | C49: 2024 Setembro | D49: 45470 | E49: 45684 | F49: =DATEDIF(Tabela153[[#This Row],[Data entrada]],Tabela153[[#This Row],[Data 2]], "M") -> 7 | G49: Manel | H49: 1300 | I49: - | J49: 2 | K49: concluded
B50: Irmãos Rodrigues | C50: 2024 Setembro | D50: 45558 | E50: 45747 | F50: =DATEDIF(Tabela153[[#This Row],[Data entrada]],Tabela153[[#This Row],[Data 2]], "M") -> 6 | G50: Sérgio | H50: 1200 | I50: - | J50: 1 | K50: concluded
B51: Fapil | C51: 2024 Setembro | D51: 45548 | E51: 45747 | F51: =DATEDIF(Tabela153[[#This Row],[Data entrada]],Tabela153[[#This Row],[Data 2]], "M") -> 6 | G51: Sérgio | H51: 1500 | I51: - | J51: 2 | K51: concluded
B52: Infinite Foundry | C52: 2024 Dezembro | D52: 45543 | E52: 45747 | F52: =DATEDIF(Tabela153[[#This Row],[Data entrada]],Tabela153[[#This Row],[Data 2]], "M") -> 6 | G52: Manel | H52: 1900 | I52: - | J52: 0 | K52: concluded
B53: SF Globallaser | C53: 45627 | D53: 45643 | E53: 45705 | G53: Sérgio | H53: 1900 | I53: 0.03 | K53: concluded
B55: Clientes ativos | C55: =COUNT(D8:D29) -> 22
B56: Clientes em hold | C56: =COUNT(E35:E46) -> 12 | H56: Active recurring | I56: Projectos ativos
B57: Clientes concluded | C57: =COUNT(D48:D53) -> 6 | G57: Marco | H57: =SUM(H9,H10,H14,H15) -> 5600 | I57: =COUNTIF(G8:G20,G10) -> 4
B58: Total | C58: =SUM(C55,C57,C56) -> 40 | G58: Manel | H58: =SUM(H12,H16) -> 2700 | I58: =COUNTIF(G8:G20,G58) -> 2
G59: Allen | H59: =SUM(H8,H11,H20) -> 3900 | I59: =COUNTIF(G8:G20,G59) -> 3
G60: Sérgio | H60: =SUM(H18+H17+H13+H35+H51+H50) -> 9500 | I60: =COUNTIF(G8:G20,G60) -> 3
G61: Sofia | H61: =H19 -> 1900 | I61: =COUNTIF(G8:G20,G61) -> 1
G62: Total | H62: =SUM(H57:H61) -> 23600 | I62: 19
C66: 2025 | D66: Entradas projetos
C67: Janeiro | D67: =COUNTIF(C8:C20,C13) -> 2
C68: Fevereiro | D68: =COUNTIF(C8:C20,C16) -> 1
C69: Março | D69: =COUNTIF(C8:C20,C19) -> 4
C70: Abril | D70: =COUNT(D21:D22,D23,D24) -> 4
C71: Maio
C72: Junho
C73: Julho
C74: Agosto
C75: Setembro
C76: Outubro
C77: Novembro
C78: Dezembro
C83: 2025 | D83: Saída de projetos
C84: Janeiro | D84: =COUNT(E49) -> 1
C85: Fevereiro | D85: =COUNT(E37,E53) -> 2
C86: Março | D86: =COUNT(D17:D20) -> 4
C87: Abril | D87: =COUNT(D21:D24) -> 4
C88: Maio
C89: Junho
C90: Julho
C91: Agosto
C92: Setembro
C93: Outubro
C94: Novembro
C95: Dezembro

Sheet Reuniões 2025
G1: Account Manager | H1: País | I1: Cliente | J1: Potencial Cliente | K1: Data | L1: Score
G2: Allen | H2: MA | I2: Arte&Mola | J2: Extra Matelas | K2: 27/05/2024
G3: Allen | H3: MA | I3: Techno Store | J3: YEP | K3: 45419
G4: Allen | H4: TU | I4: Arte&Mola | J4: Materna | K4: 45572
G5: Allen | H5: MA | I5: Techno Store | J5: Yaratech | K5: 17/07/2024
G6: Vânia | H6: KW | I6: New Mattress | J6: La Casa | K6: 24/07/2024
G7: Vânia | H7: UAE | I7: Farimovel | J7: Magna General Trading | K7: 24/07/2024
G8: Allen | H8: LI | I8: Gin T | J8: Abi Ramia Bros | K8: 25/07/2024
G9: Allen | H9: AL | I9: Arte&Mola | J9: La Belle Literie | K9: 25/07/2024
G10: Vânia | H10: QA | I10: Farimovel | J10: Fab Furnish | K10: 26/07/2024
G11: Marco | H11: LI | I11: Delta | J11: Malia Group | K11: 29/07/2024
G12: Vânia | H12: UAE | I12: New Mattress | J12: Bafte | K12: 29/07/2024
G13: Isabela | H13: UAE | I13: FM Têxteis | J13: Jokes Aside | K13: 30/07/2024
G14: Allen | H14: LI | I14: Gin T | J14: Barlivery | K14: 31/07/2024
G16: Marco | H16: UAE | I16: Granidense | J16: Emirates Marble & Granite | K16: 45299
G17: Marco | H17: UAE | I17: Artnovion | J17: Bishop Design | K17: 45330
G18: Marco | H18: TU | I18: Vittawood | J18: General Distribuition Placo | K18: 45330
G19: Marco | H19: UAE | I19: Delta | J19: Al Abdullah Group | K19: 45420
G20: Isabela | H20: UAE | I20: Gema | J20: Sand Circus | K20: 45451
G21: Marco | H21: SA | I21: Granidense | J21: Al-Rahmani Group | K21: 45451
G22: Allen | H22: LI | I22: Gin T | J22: Dekkeni | K22: 45481
G23: Isabela | H23: SA | I23: FM Têxteis | J23: One of a Kind | K23: 45512
G24: Vânia | H24: MA | I24: New Mattress | J24: Mon Mantelas | K24: 45634
G25: Vânia | H25: SA | I25: Farimovel | J25: Majed Harasani Design | K25: 13/8/2024
G26: Marco | H26: UAE | I26: Recheio | J26: FJX | K26: 28/08/2024
G28: Allen | H28: LI | I28: Gin T | J28: Abi Ramia Bros | K28: 45331
G29: Marco | H29: SA | I29: Arxi | J29: NSK Consulting | K29: 45537
G30: Marco | H30: UAE | I30: Artnovion | J30: DZ Design | K30: 45538
G31: Allen | H31: TU | I31: Techno Store | J31: Ranim Distribution | K31: 45574
G32: Marco | H32: SA | I32: Vittawood | J32: STQ Group | K32: 45545
G33: Marco | H33: SA | I33: Arxi | J33: Agap2IT | K33: 45547
G34: Marco | H34: SA | I34: Granidense | J34: NBR Centre | K34: 45548
G35: Allen | H35: UAE | I35: Gin T | J35: Centaurus | K35: 17/09/2024
G36: Allen | H36: MA | I36: Arte&Mola | J36: Arton Confort | K36: 19/09/2024
G37: Marco | H37: QA | I37: Delta | J37: Al Maya | K37: 45554
G38: Marco | H38: EG | I38: Vittawood | J38: Egyptian Supplies | K38: 45537
G39: Allen | H39: MA | I39: Gin T | J39: Bourchanin&Cie | K39: 26/09/2024
G40: Marco | H40: TU | I40: Farvoli | J40: ITAK | K40: 45301
G41: Allen | H41: TU | I41: Techno Store | J41: Tunewtech | K41: 45332
G42: Allen | H42: LI | I42: Gin T | J42: Ziad Chanine | K42: 45392
G43: Marco | H43: NG | I43: Vittawood | J43: Skynet | K43: 45545
G44: Marco | H44: NG | I44: Vittawood | J44: Tormek Global | K44: 45545
G45: Marco | H45: EG | I45: Delta | J45: Emkay Foods | K45: 45575
G46: Allen | H46: MA | I46: Techno Store | J46: Kids Jouets | K46: 17/10/2024
G47: Marco | H47: QA | I47: Granidense | J47: HBK Contracting | K47: 21/10/2024
G48: Marco | H48: TU | I48: Farvoli | J48: Domaine Chograne | K48: 21/10/2024
G49: Marco | H49: TQ | I49: Farvoli | J49: Turqagro Group | K49: 24/10/2024
G50: Marco | H50: EG | I50: Farvoli | J50: Olive Garden | K50: 28/10/2025
G51: Allen | H51: UAE | I51: Gin T | J51: West Zone Group | K51: 22/10/2024
G52: Allen | H52: SN | I52: Techno Store | J52: CMS Shop | K52: 22/10/2024
G53: Allen | H53: MA | I53: Arte&Mola | J53: Arton Confort | K53: 23/10/2024
G54: Allen | H54: SN | I54: Techno Store | J54: Marché Alizé | K54: 23/10/2024
G55: Marco | H55: SA | I55: Alpha Gamer | J55: AIC | K55: 29/10/2025
G56: Marco | H56: EG | I56: Infinite Foundry | J56: Al-Ahram Group | K56: 29/10/2026
G57: Allen | H57: SN | I57: Techno Store | J57: City Phone | K57: 24/10/2024
G58: Allen | H58: NG | I58: Techno Store | J58: Computer Village Mart | K58: 45484
G59: Allen | H59: NG | I59: Techno Store | J59: Doncent Electronics | K59: 45515
G60: Allen | H60: NG | I60: Techno Store | J60: TD Gold Store | K60: 45607
G61: Allen | H61: OM | I61: Freire Lobo | J61: Universe Lines International | K61: 45515 | L61: 4
G62: Sérgio | H62: TN | I62: Fapil | J62: Global Test Tunisie | K62: 45514
G63: Sérgio | H63: MA | I63: Fapil | J63: La Brosse Maroc | K63: 45545
G64: Sérgio | H64: MA | I64: Fapil | J64: Mani Distribuition | K64: 24/10/2024
G65: Sérgio | H65: MA | I65: Fapil | J65: Flexifloor Maroc | K65: 45515
G66: Sérgio | H66: BH | I66: JF Almeida | J66: A.R.Kamal & Sons Co.
G67: Sérgio | H67: EG | I67: JF Almeida | J67: Valentina Linens | K67: 16/10/2024
G68: Sérgio | H68: EG | I68: JF Almeida | J68: Cotton Land | K68: 45454
G69: Isabela | H69: EG | I69: CRAFIL | J69: Eye of Ra | K69: 24/10/2024
G70: Isabela | H70: EG | I70: CRAFIL | J70: New Trend Egypt | K70: 14/10/2024
G71: Isabela | H71: EG | I71: CRAFIL | J71: Dolphin Garments | K71: 24/09/2024
G72: Isabela | H72: UAE | I72: Cubu Fitness | J72: FLTRD | K72: 18/09/2024
G73: Isabela | H73: UAE | I73: Givachoice | J73: Pearla | K73: 19/09/2024
G74: Isabela | H74: EG | I74: CRAFIL | J74: Akay Garments | K74: 45635
G75: Isabela | H75: SA | I75: FM TÊXTEIS | J75: Kaafmeem | K75: 45481
G76: Isabela | H76: SA | I76: GEMA | J76: Sand Circus | K76: (VERIFICAR)
G77: Isabela | H77: SA | I77: GEMA | J77: (VERIFICAR) | K77: (VERIFICAR)
G78: Isabela | H78: SA | I78: GEMA | J78: (VERIFICAR) | K78: (VERIFICAR)
G79: Isabela | H79: SA | I79: GEMA | J79: (VERIFICAR) | K79: (VERIFICAR)
G80: Marco | H80: SA | I80: Alpha Gamer | J80: FNAC SA | K80: -
G81: Marco | H81: TU | I81: Alpha Gamer | J81: FNAC TU | K81: -
G82: Marco | H82: SA | I82: Alpha Gamer | J82: Game ON | K82: -
G83: Marco | H83: QA | I83: Alpha Gamer | J83: Innox Tech | K83: -
G84: Marco | H84: KU | I84: Alpha Gamer | J84: Al Waha Computer | K84: -
G85: Marco | H85: SA | I85: Vittawood | J85: Ferruti | K85: -
G86: Marco | H86: LI | I86: Vittawood | J86: MTCC Group | K86: -
G87: Marco | H87: EG | I87: Vittawood | J87: Al Jaber | K87: -
... G108: Marco | H108: SA | I108: RJB Home | J108: Avario | K108: -
G109: WEEK 46 | H109: WEEK 46 | I109: WEEK 46 | J109: WEEK 46 | K109: WEEK 46 | L109: WEEK 46
G110: Marco | H110: GH | I110: Vittawood | J110: Leader Price Ghana | K110: 46340
G111: Marco | H111: EG | I111: Infinite Foundry | J111: Al-Ahram Group, FU | K111: 46337
G112: Marco | H112: KU | I112: Alpha Gamer | J112: 8-Bit | K112: 46338
G113: Sérgio | H113: QA | I113: Socutel | J113: Five Continental | K113: 45637 | L113: 4
G114: Sérgio | H114: GH | I114: Techno Store | J114: Jumia Ghana | K114: 14/11/2024 | L114: 4
G115: Sérgio | H115: SN | I115: Techno Store | J115: City Phone | K115: 14/11/2024 | L115: -
G116: Marco | H116: SA | I116: Granidense | J116: Blue Sea Global | K116: 46340 | L116: 1
G117: WEEK 47 | H117: WEEK 47 | I117: WEEK 47 | J117: WEEK 47 | K117: WEEK 47 | L117: WEEK 47
G118: Marco | H118: NG | I118: Techno Store | J118: PVT Gadgets | K118: 18/11/2024
G119: Marco | H119: SA | I119: Artnovion | J119: Arabian Smart Homes | K119: 46346 | L119: 4
G120: Isabela | H120: EAU | I120: Cubu Fitness | J120: Ether | K120: 45615 | L120: 3
G121: Sérgio | H121: TN | I121: Socutel | J121: Miyado Cuisine | K121: 45616 | L121: 4
G122: Marco | H122: SA | I122: Alpha Gamer | J122: Pre Game SA | K122: 45617 | L122: -
...

Sheet Reuniões 2026
A1: Account Manager | B1: País | C1: Cliente | D1: Potencial Cliente | E1: Data | F1: Score
A2: WEEK 1 | B2: WEEK 1 | C2: WEEK 1 | D2: WEEK 1 | E2: WEEK 1 | F2: WEEK 1
A3: Maiza/Allen/Pedro | B3: Reunião de Alinhamento | C3: Bocean | D3: MAAB | E3: 46024
A4: WEEK 2 | B4: WEEK 2 | C4: WEEK 2 | D4: WEEK 2 | E4: WEEK 2 | F4: WEEK 2
A5: Allen | B5: UAE | C5: Alpine Seafood | D5: Chef Middle East | E5: 46027 | F5: 4
A6: Julia | B6: SA | C6: Sweet and Sugar | D6: Balsharaf Group | E6: 46143 | F6: N/A
A7: Julia | B7: SA | C7: Yogoody | D7: Nutrition Diet Center | E7: 46143 | F7: N/A
A8: Maíza | B8: EG | C8: Altix | D8: MAM Electric | E8: 46143 | F8: 4
A9: Allen | B9: UAE | C9: Artnovion | D9: Salt Technology Services | E9: 46174 | F9: 4
A10: Allen | B10: UAE | C10: Districaia | D10: Joud Coffee | E10: 46174 | F10: 4
A11: Julia | B11: SA | C11: Yogoody | D11: Almunajem | E11: 46174 | F11: 4
A12: Allen | B12: KW | C12: Emotional Brands | D12: Inside Design Company | E12: 46028 | F12: 4
A13: Allen | B13: UAE | C13: Sutol | D13: Dennemeyer | E13: 46204 | F13: 1
A14: Allen | B14: QA | C14: Emotional Brands | D14: Al Jameel Showroom | E14: 46030 | F14: 4
A15: Allen | B15: KW | C15: Delta Cafés | D15: Kuwait Proteins | E15: 46235 | F15: 3
A16: David | B16: SN | C16: Genan | D16: MangoSports | E16: 46235 | F16: 3
A17: Julia | B17: GH | C17: Yogoody | D17: Rafimex | E17: 46266 | F17: 4
A18: Ana | B18: Reunião Status | C18: Core Cocept | D18: MAAB | E18: 46030
A19: Ana | B19: Reunião Status | C19: Fernandes e Sampaio | D19: MAAB | E19: 46030
A20: Ana /Maiza | B20: Reunião de Projeto | C20: Altix | D20: MAAB | E20: 46030
A21: Ana | B21: Reunião Status | C21: Coltec | D21: MAAB | E21: 46030
A22: Ana | B22: Reunião Status | C22: Yogoody | D22: MAAB | E22: 46030
A23: Ana | B23: Reunião Status | C23: ALTIX | D23: MAAB | E23: 46029
A24: Maiza/Ana | B24: Reunião AlInhamento | C24: Animovel | D24: MAAB | E24: 46028
A25: Allen/João/Pedro/Ana | B25: Reunião de Projeto | C25: Freshland | D25: MAAB | E25: 46027
A26: Ana/Julia | B26: Reunião de Projeto | C26: SONATURAL | D26: MAAB | E26: 46027
A27: WEEK 3 | B27: WEEK 3 | C27: WEEK 3 | D27: WEEK 3 | E27: WEEK 3 | F27: WEEK 3
A28: Julia | B28: UAE | C28: Fernandes e Sampaio | D28: UNLO | E28: 46357 | F28: N/A
A29: Julia | B29: SA | C29: SONATURAL | D29: Rawasi Group | E29: 46357 | F29: 3
A30: David | B30: QA | C30: Artnovion | D30: Execute Interiors | E30: 13/1/2026 | F30: 3
A31: David | B31: BR | C31: Core Concept | D31: PSA Arquitetura | E31: 13/1/2026 | F31: N/A
A32: Julia | B32: UAE | C32: Districaia | D32: DP World | E32: 13/1/2026 | F32: N/A
A33: Julia | B33: QA | C33: Delta Cafés | D33: Ali Bin Ali | E33: 13/1/2026 | F33: 3
A34: Maíza | B34: EG | C34: Altix | D34: ANNCO | E34: 13/1/2026 | F34: 4
A35: Maíza | B35: KSA | C35: Aquecinox | D35: Pure Seasons | E35: 13/1/2026 | F35: N/A
A36: David | B36: MA | C36: Denodl | D36: CP Tech | E36: 14/1/2026 | F36: N/A
A37: David | B37: MA | C37: Denodl | D37: IrriPower | E37: 14/1/2026 | F37: 3
A38: Julia | B38: UAE | C38: Alpine Seafood | D38: Organic Food & Cafe | E38: 14/1/2026 | F38: N/A
A39: David | B39: UAE | C39: Artnovion | D39: Focus Acoustics | E39: 15/1/2026 | F39: 3
A40: David | B40: UAE | C40: Artnovion | D40: Design Young | E40: 15/1/2026 | F40: 4
A41: David | B41: MR | C41: Garsteel | D41: Abdouly Holding | E41: 15/1/2026 | F41: 3
A42: David | B42: MR | C42: Termopainel | D42: Abdouly Holding | E42: 15/1/2026 | F42: 4
A43: Maíza | B43: KSA | C43: Aquecinox | D43: Nesma Partners | E43: 15/1/2026 | F43: 2
A44: Julia | B44: UAE | C44: Fernandes e Sampaio | D44: Sachin Banodkar | E44: 16/1/2026 | F44: 4
A45: Julia | B45: SA | C45: Districaia | D45: Nutrition Diet Center | E45: 16/1/2026 | F45: N/A
A46: David | B46: BR | C46: Core Concept | D46: STarq Arquitetura | E46: 16/1/2026 | F46: 4
A47: David | B47: BR | C47: Core Concept | D47: ACR Arquitetos Associados | E47: 16/1/2026 | F47: N/A
A48: Ana | B48: Reunião Status | C48: Denodl | D48: MAAB | E48: 45673
A49: Ana | B49: Reunião de Projeto | C49: Animovel | D49: MAAB | E49: 45670
A50: Ana | B50: Reunião Status | C50: Emotional Brands | D50: MAAB | E50: 45670
A51: Ana/Julia/Pedro | B51: Reunião de Projeto | C51: Fernandes e Sampaio | D51: MAAB | E51: 45670
A52: Ana | B52: Reunião Status | C52: Genan | D52: MAAB | E52: 45670
A53: Ana/ Maiza | B53: Reunião de Projeto | C53: Bocean | D53: MAAB | E53: 45669
A54: WEEK 4 | B54: WEEK 4 | C54: WEEK 4 | D54: WEEK 4 | E54: WEEK 4 | F54: WEEK 4
A55: Julia | B55: UAE | C55: Fernandes e Sampaio | D55: Italian Footwear Solution | E55: 19/01/2026 | F55: 3
A56: Maíza | B56: KW | C56: Emotional Brands | D56: Bonyan Group | E56: 19/01/2025 | F56: 4
A57: Maíza | B57: EG | C57: Coltec | D57: Nile Textile | E57: 20/01/2025 | F57: 3
A58: David | B58: SN | C58: Garsteel | D58: Holding Willix | E58: 20/01/2025 | F58: Presencial
A59: David | B59: SN | C59: Core Concept | D59: Holding Willix | E59: 20/01/2025 | F59: Presencial
A60: David | B60: SN | C60: MSRI | D60: Holding Willix | E60: 20/01/2025 | F60: Presencial
A61: David | B61: SN | C61: Natstone | D61: Holding Willix | E61: 20/01/2025 | F61: Presencial
A62: David | B62: SN | C62: Genan | D62: Holding Willix | E62: 20/01/2025 | F62: Presencial
A63: David | B63: SN | C63: Termopainel | D63: Holding Willix | E63: 20/01/2025 | F63: Presencial
A64: David | B64: DZ | C64: Genan | D64: Teslia | E64: 21/01/2025 | F64: 4
A65: Maíza | B65: UAE | C65: Aquecinox | D65: Zenith | E65: 21/01/2025 | F65: N/A
A66: David | B66: CI | C66: Core Concept | D66: BAOBAB Architects | E66: 21/01/2025 | F66: N/A
A67: David | B67: DZ | C67: Termopainel | D67: NATURETRANCHE | E67: 21/01/2025 | F67: N/A
A68: David | B68: MA | C68: Denodl | D68: AQUA4D | E68: 22/01/2025 | F68: 4
A69: Maíza | B69: UAE | C69: Animovel | D69: ABRA | E69: 22/01/2025 | F69: 4
A70: David | B70: CI | C70: Core Concept | D70: Superlimão | E70: 21/01/2025 | F70: 4
A71: David | B71: CI | C71: Core Concept | D71: Bacco Arquitetos Associados | E71: 21/01/2025 | F71: N/A
A72: Ana | B72: Reunião Status | C72: Districaia | D72: MAAB | E72: 45679
A73: Ana | B73: Alinhamento | C73: Resuno Matinal | D73: MAAB | E73: 46043
A74: Ana | B74: Reunião Status | C74: SONATURAL | D74: MAAB | E74: 46042
A75: WEEK 5 | B75: WEEK 5 | C75: WEEK 5 | D75: WEEK 5 | E75: WEEK 5 | F75: WEEK 5
A76: Julia | B76: UAE | C76: Fernandes e Sampaio | D76: Hoog Store | E76: 26/01/2026 | F76: 3
A77: Maíza | B77: UAE | C77: ConnecTextile | D77: ZG Traders | E77: 27/01/2026 | F77: N/A
A78: Allen | B78: MA | C78: Sutol | D78: Groupe Rahal | E78: 27/01/2026 | F78: 4
A79: David | B79: OM | C79: CoreConcept | D79: Espace Engineering Consultants | E79: 27/01/2026 | F79: 4
A80: David | B80: DZ | C80: Termopainel | D80: Eco Commerce International | E80: 27/01/2026 | F80: 4
A81: David | B81: MA | C81: Denodl | D81: Agrolora | E81: 28/01/2026 | F81: 3
A82: Maíza | B82: KSA | C82: Aquecinox | D82: SaudiBoilers | E82: 28/01/2026 | F82: N/A
A83: Allen | B83: UAE | C83: Fernandes e Sampaio | D83: MENA Lifestyle | E83: 29/01/2026 | F83: Aguarda resposta do cliente
A84: Maíza | B84: KW | C84: Altix | D84: Al Jassar | E84: 29/01/2026 | F84: 4
A85: David | B85: JO | C85: CoreConcept | D85: Sanabel Landscape Architecture | E85: 29/01/2026 | F85: 4
A86: David | B86: MA | C86: Denodl | D86: ARWA Solutions | E86: 29/01/2026 | F86: 4
A87: David | B87: MR | C87: Garsteel | D87: SEA Engeniring | E87: 29/01/2026 | F87: 3
A88: David | B88: EG | C88: Genan | D88: Hoppec | E88: 30/01/2026 | F88: 4
A89: Ana / Pedro | B89: Apresentação - Associação | C89: AECOA | D89: MAAB | E89: 46048
A90: Ana | B90: Reunião Status | C90: Aquecinox | D90: MAAB | E90: 46050
A91: Ana | B91: Reunião Status | C91: Coltec | D91: MAAB | E91: 46050
A92: Ana /Maiza/David | B92: Reunião de Alinhamento | C92: PHF /SINGULA | D92: MAAB | E92: 46050
A93: Ana | B93: Reunião Status | C93: Altix | D93: MAAB | E93: 46051
A94: Ana /Allen | B94: Reunião de Alinhamento | C94: FRUTORRA | D94: MAAB | E94: 46051
A95: Ana | B95: Reunião Status | C95: Denodl | D95: MAAB | E95: 46052
A96: WEEK 6 | B96: WEEK 6 | C96: WEEK 6 | D96: WEEK 6 | E96: WEEK 6 | F96: WEEK 6
A97: Allen | B97: UAE | C97: Fernandes e Sampaio | D97: Shane Hassan | E97: 46055 | F97: 4
A98: David | B98: MA | C98: Denodl | D98: EarthSense | E98: 46055 | F98: 4
A99: David | B99: DZ | C99: Termopainel | D99: NATURETRANCHE | E99: 46055 | F99: 4
A100: Maíza | B100: OM | C100: Altix | D100: FTS | E100: 46055 | F100: 4
...

Sheet Pagamentos
A1: Nome | B1: Inicio | C1: Dia começo | D1: Monthly Fee | E1: Success Fee | F1: Setembro | G1: Setembro | H1: Outubro | I1: Novembro | J1: Dezembro | K1: Enero | L1: Febrero | M1: Marzo | N1: Abril | O1: Mayo | P1: Junio
A2: Delta | B2: 45444 | C2: 1 de junho | D2: 1100 | E2: -
A3: GinT | B3: 45474 | C3: 9 de julho | D3: 1500 | E3: -
A4: Givachoice | B4: 45444 | C4: 27 de junho | D4: 2.400 € | E4: -
A5: Aquecinox | B5: 45690 | C5: 5 de fevereiro | D5: 1500
A6: Core Concept | B6: 45718 | C6: 3 de março | D6: 1900 | E6: 0.05
A7: Genan | B7: 45748 | C7: 4 de abril | D7: 1900 | E7: 0.05
A8: Freshland Harvest | B8: 45778 | C8: 12 de maio | D8: 1500 | E8: 0.05
A9: Happy Probability | B9: 45839 | C9: 3 de julho | D9: 1300 | E9: 0.05
A10: Garsteel | B10: 45839 | C10: 14 de julho | D10: 1900 | E10: 0.03
A11: Sutol | B11: 45839 | C11: 7 de julho | D11: 1900 | E11: 0.03
A12: Compincar | B12: 45901 | C12: 1 de setembro | D12: 1500
A13: Altix | B13: 45901 | C13: 1 de setembro | D13: 1200 | E13: 0.06
A14: Districaia | B14: 45931 | C14: 8 de outubro | D14: 1500 | E14: 0.05
A15: NCFHK | B15: 45931 | C15: 3 de novembro | D15: 1500 | E15: 0.05
A16: GL | B16: 45992 | C16: 30 de dezembro | D16: 1200 | E16: 0.05
A17: Denodl | B17: 46023 | C17: 5 de janeiro | D17: 2.100 €
A18: Animovel | B18: 46023 | C18: 6 de janeiro | D18: 1750 | E18: 0.05
A19: PHF | B19: 46023 | C19: 23 de janeiro | D19: 1500 | E19: 0.05
A20: Frutorra | B20: 46023 | C20: 28 de janeiro | D20: 1300 | E20: 0.02
A21: Innatam | B21: 46054 | C21: 2 de fevereiro | D21: 1500 | E21: 0.05
A22: Pavinorte | B22: 46056 | C22: 18 de fevereiro | D22: 1900 | E22: 0.05
A23: Madeivouga | B23: 46056 | C23: 18 de fevereiro | D23: 1900 | E23: 0.05
A24: Sagiper | B24: 46084 | C24: 4 de março | D24: 1750 | E24: 0.05
A25: Topeca | B25: 46084 | C25: 5 de março | D25: 1750 | E25: 0.05
A26: Urbiagua | B26: 46084 | C26: 17 de março | D26: 1300 | E26: 0.05
A27: Ibernop | B27: 46083 | C27: 27 de março | D27: 1750 | E27: 0.05
A28: Atlantic Wood | B28: 46083 | C28: 31 de março | D28: 1900 | E28: 0.05
A29: Magic Way | B29: 46083 | C29: 31 de março | D29: 750 | E29: 0.05
... A33: Conformetal | B33: 46143 | C33: 1 de maio | D33: 1500 | E33: 0.05
A34: Tecnifreza | B34: 46143 | C34: 1 de maio | D34: 1250 | E34: 2% - 4%
A35: Grupo Eleva | B35: 46143 | C35: 1 de maio | D35: 500
A36: PTGAL Business | B36: 46143 | C36: 26 de maio | D36: 1500 | E36: 0.02
A37: Helitene | B37: 46174 | C37: 1 de junho | D37: 1750 | E37: 0.02
A38: Carldora | B38: 46174 | C38: 1 de junho | D38: 1500 | E38: 0.02
A39: Umbelino Monteiro | B39: 46023 | C39: 23 de janeiro | D39: 1500
